tronnetpy/__init__.py
tronnetpy/main.py
tronnetpy-0.0.1.dist-info/LICENSE.txt
tronnetpy-0.0.1.dist-info/METADATA
tronnetpy-0.0.1.dist-info/WHEEL
tronnetpy-0.0.1.dist-info/top_level.txt
tronnetpy-0.0.1.dist-info/RECORD
