Metadata-Version: 2.1
Name: tronnetpy
Version: 0.0.1
Summary: tronnetpy library for Python
Author: felixtron
Author-email: qutyjeje@joliys.pro
License: MIT
Project-URL: Source Repository, https://github.com/andelf/tronpy
License-File: LICENSE.txt
Requires-Dist: requests
